{
  "fontFamily": "Arial, Helvetica, sans-serif",
  "values": [
    {
      "avg": 4.503602662271701,
      "size": 8,
      "height": 9.09765625
    },
    {
      "avg": 5.631334769807512,
      "size": 10,
      "height": 11.125
    },
    {
      "avg": 6.755404399572578,
      "size": 12,
      "height": 13.640625
    },
    {
      "avg": 9.007208293789866,
      "size": 16,
      "height": 17.61328125
    },
    {
      "avg": 11.26267232727841,
      "size": 20,
      "height": 22.75
    },
    {
      "avg": 18.018086544248956,
      "size": 32,
      "height": 35.8671875
    },
    {
      "avg": 27.02895907702014,
      "size": 48,
      "height": 53.953125
    }
  ]
}