{
  "fontFamily": "Verdana, Geneva, sans-serif",
  "values": [
    {
      "avg": 1.9013624924879808,
      "height": 3.55078125,
      "size": 3
    },
    {
      "avg": 5.070299979967949,
      "height": 9.54296875,
      "size": 8
    },
    {
      "avg": 6.337874974959936,
      "height": 12.015625,
      "size": 10
    },
    {
      "avg": 7.605449969951923,
      "height": 14.5,
      "size": 12
    },
    {
      "avg": 10.140599959935898,
      "height": 19.5,
      "size": 16
    },
    {
      "avg": 12.675749949919872,
      "height": 24.03125,
      "size": 20
    },
    {
      "avg": 20.281199919871796,
      "height": 38.52734375,
      "size": 32
    },
    {
      "avg": 30.421799879807693,
      "height": 58.5,
      "size": 48
    }
  ]
}